TUKAkit/__init__.py
TUKAkit/parse.py
TUKAkit/_pd_cache/__init__.py
TUKAkit/_util/__init__.py
TUKAkit/_util/_critera.py
TUKAkit/testing/__init__.py
TUKAkit/testing/_test.py
TUKAkit/testing/data/Ac2IrRh.cif
TUKAkit/testing/data/CaO2.cif
TUKAkit/testing/data/Na2O2.cif
TUKAkit/testing/data/NaCaO3.cif
TUKAkit-0.0.2.dist-info/METADATA
TUKAkit-0.0.2.dist-info/WHEEL
TUKAkit-0.0.2.dist-info/top_level.txt
TUKAkit-0.0.2.dist-info/RECORD
