Metadata-Version: 2.1
Name: TUKAkit
Version: 0.0.2
Summary: Toolkit for evaluating crystal structures with the TUKA criteria
Home-page: https://github.com/Bin-Cao/TUKA-criteria
Author: Bin Cao
Author-email: binjacobcao@gmail.com
Maintainer: Bin Cao
Maintainer-email: binjacobcao@gmail.com
License: MIT License
Classifier: Development Status :: 3 - Alpha
Classifier: Intended Audience :: Science/Research
Classifier: Topic :: Scientific/Engineering :: Chemistry
Classifier: Topic :: Scientific/Engineering :: Artificial Intelligence
Classifier: License :: OSI Approved :: MIT License
Classifier: Programming Language :: Python :: 3
Classifier: Programming Language :: Python :: 3.6
Classifier: Programming Language :: Python :: 3.7
Classifier: Programming Language :: Python :: 3.8
Classifier: Programming Language :: Python :: 3.9
Requires-Python: >=3.6
